{ "annotation": [ { "charNum": "1", "label": "사실형", "length": 31, "text": "경제 성장과 괴리된 고용이 한국 경제 발목을 잡고 있다.", "value": { "text_id": "1", "word_num": 9, "핵심동사": "잡고", "확실성": "확실", "극성": "긍정", "시제": "현재", "key_word": " " } }, { "charNum": "32", "label": "사실형", "length": 69, "text": "금융위기 후에는 고용 없는 성장이라는 일반적인 현상을 뛰어넘어 신규 일자리 자체가 생기지 않는 심각한 사태에 직면하고 있다.", "value": { "text_id": "2", "word_num": 17, "핵심동사": "직면하고", "확실성": "확실", "극성": "부정", "시제": "현재", "key_word": " " } }, { "charNum": "101", "label": "사실형", "length": 40, "text": "2004년 이후 몇 년간 지속됐던 성장 시기에 고용 창출은 제한적이었다.", "value": { "text_id": "3", "word_num": 10, "핵심동사": "제한적이었다", "확실성": "확실", "극성": "긍정", "시제": "과거", "key_word": " " } }, { "charNum": "141", "label": "사실형", "length": 30, "text": "성장률은 높아졌지만 일자리 창출 폭은 제자리걸음이었다.", "value": { "text_id": "4", "word_num": 6, "핵심동사": "제자리걸음이었다", "확실성": "확실", "극성": "긍정", "시제": "과거", "key_word": " " } }, { "charNum": "171", "label": "사실형", "length": 72, "text": "2000년 18.1명이던 전 산업의 취업유발계수(10억원 생산 시 만들어지는 일자리 수)는 2007년에는 13.9명까지 하락했다.", "value": { "text_id": "5", "word_num": 13, "핵심동사": "하락했다", "확실성": "확실", "극성": "긍정", "시제": "과거", "key_word": " " } }, { "charNum": "243", "label": "사실형", "length": 129, "text": "윤증현 기획재정부 장관은 지난 4일 기자간담회에서 ＂고용과 성장이 비례하지 않는 것이 가장 큰 문제＂라며 ＂예전에는 성장률 1%면 고용이 8만~9만명 정도 창출됐는데 요즘엔 1% 성장에 3만~4만명 고용에 그치고 있다＂고 지적했다.", "value": { "text_id": "6", "word_num": 29, "핵심동사": "지적했다", "확실성": "확실", "극성": "긍정", "시제": "과거", "key_word": " " } }, { "charNum": "372", "label": "사실형", "length": 73, "text": "금융위기 이후 경제 회복세가 나타나고 있지만 막상 고용 창출 폭은 커지지 않아 ＇고용 없는 경기 회복＇에 대한 염려도 커지고 있다.", "value": { "text_id": "7", "word_num": 20, "핵심동사": "커지고", "확실성": "확실", "극성": "긍정", "시제": "현재", "key_word": " " } }, { "charNum": "445", "label": "사실형", "length": 74, "text": "이와 같은 성장과 고용 간 괴리 현상은 한국 경제 성장을 이끌었던 수출/제조업에서 고용 창출이 예전만큼 이뤄지지 않고 있기 때문이다.", "value": { "text_id": "8", "word_num": 19, "핵심동사": "때문이다", "확실성": "확실", "극성": "부정", "시제": "현재", "key_word": " " } }, { "charNum": "519", "label": "사실형", "length": 49, "text": "수출의 취업유발계수는 2000년 15.3명에서 2007년에는 9.4명으로 대폭 하락했다.", "value": { "text_id": "9", "word_num": 8, "핵심동사": "하락했다", "확실성": "확실", "극성": "긍정", "시제": "과거", "key_word": " " } }, { "charNum": "568", "label": "사실형", "length": 156, "text": "류지성 삼성경제연구소 연구위원은 ＂단순 조립형 제조업은 외국으로 이전되고 고용 창출이 상대적으로 적은 IT 제조업 비중이 높아지면서 고용 창출력이 저하되고 있다＂며 ＂여전히 수출 제조업이 중심인 한국 경제 특성으로 볼 때 이와 같은 괴리 현상은 계속될 것으로 보인다＂고 진단했다.", "value": { "text_id": "10", "word_num": 37, "핵심동사": "진단했다", "확실성": "확실", "극성": "긍정", "시제": "과거", "key_word": " " } }, { "charNum": "724", "label": "사실형", "length": 39, "text": "고용 창출 효과가 큰 서비스 산업이 침체돼 있는 것도 문제로 지적된다.", "value": { "text_id": "11", "word_num": 11, "핵심동사": "지적된다", "확실성": "확실", "극성": "긍정", "시제": "현재", "key_word": " " } }, { "charNum": "763", "label": "사실형", "length": 51, "text": "서비스업의 취업유발계수는 18.1명(2007년)으로 제조업(9.2명)에 비해 두 배나 높다.", "value": { "text_id": "12", "word_num": 8, "핵심동사": "높다", "확실성": "확실", "극성": "긍정", "시제": "현재", "key_word": " " } }, { "charNum": "814", "label": "사실형", "length": 70, "text": "하지만 한국에서 서비스업 고용 비중은 66.7%(2007년)로 경제협력개발기구(OECD) 30개국 중 20위 수준에 불과하다.", "value": { "text_id": "13", "word_num": 12, "핵심동사": "불과하다", "확실성": "확실", "극성": "긍정", "시제": "현재", "key_word": " " } }, { "charNum": "884", "label": "사실형", "length": 44, "text": "그나마 서비스업 취업도 도소매/음식/숙박업 등 저부가가치 산업에 집중되어 있다.", "value": { "text_id": "14", "word_num": 9, "핵심동사": "집중되어", "확실성": "확실", "극성": "긍정", "시제": "현재", "key_word": " " } } ], "dupLabelYn": "Y", "metaData": { "ID": "130603", "FILENAME": "130603.json", "MEDIA_TYPE": "뉴스", "MEDIA_NAME": "매일경제", "CATEGORY": "금융", "PUBDATE": "20100106", "SENTENCE": "14" } } 