{ "annotation": [ { "charNum": "1", "label": "예측형", "length": 74, "text": "외환은행의 론스타 불법 매각 소송이 상고심에서도 무죄 판결로 나옴에 따라 외환은행 인수를 위한 국내외 쟁탈전도 다시 불붙을 전망이다.", "value": { "text_id": "1", "word_num": 18, "핵심동사": "전망이다", "확실성": "확실", "극성": "긍정", "시제": "미래", "key_word": "전망이다" } }, { "charNum": "75", "label": "예측형", "length": 75, "text": "이에 따라 KB 사태 후폭풍에 휩싸일 조짐을 보이던 금융권 이슈는 상반기 중 빠르게 인수·합병(M&A) 쪽으로 중심을 이동할 조짐이다.", "value": { "text_id": "2", "word_num": 18, "핵심동사": "조짐이다", "확실성": "확실", "극성": "긍정", "시제": "미래", "key_word": "조짐이다" } }, { "charNum": "150", "label": "예측형", "length": 63, "text": "이에 따라 KB 사태에 쏠려 있는 금융권 이목이 우리금융과 외환은행 M&A 문제로 급격히 이동할 것으로 예상된다.", "value": { "text_id": "3", "word_num": 16, "핵심동사": "예상된다", "확실성": "불확실", "극성": "긍정", "시제": "현재", "key_word": "예상된다" } }, { "charNum": "213", "label": "추론형", "length": 20, "text": "무엇보다 조직 안정이 최우선 과제다.", "value": { "text_id": "4", "word_num": 5, "핵심동사": "과제다", "확실성": "확실", "극성": "긍정", "시제": "현재", "key_word": "과제다" } }, { "charNum": "233", "label": "예측형", "length": 45, "text": "그러나 원점으로 돌아온 KB금융지주 회장 선출까지는 상당한 시간이 걸릴 전망이다.", "value": { "text_id": "5", "word_num": 10, "핵심동사": "전망이다", "확실성": "불확실", "극성": "긍정", "시제": "현재", "key_word": "전망이다" } }, { "charNum": "278", "label": "예측형", "length": 86, "text": "새로운 회추위가 구성돼 후보를 추천하기까지 적어도 두 달 이상 걸리는 만큼 오는 3월 정기 주주총회 직전에 가서야 차기 회장 문제가 거론될 것으로 보인다.", "value": { "text_id": "6", "word_num": 23, "핵심동사": "보인다", "확실성": "불확실", "극성": "긍정", "시제": "미래", "key_word": "보인다" } } ], "dupLabelYn": "Y", "metaData": { "ID": "130576", "FILENAME": "130576.json", "MEDIA_TYPE": "뉴스", "MEDIA_NAME": "매일경제", "CATEGORY": "금융", "PUBDATE": "20100104", "SENTENCE": "6" } } 