{ "annotation": [ { "charNum": "1", "label": "대화형", "length": 45, "text": "`하루빨리 구조조정 대상이 가려져야지, 신규 차입도 어렵고 정말 피가 마릅니다.`", "value": { "text_id": "1", "word_num": 10, "핵심동사": "마릅니다", "확실성": "확실", "극성": "긍정", "시제": "현재", "key_word": " " } }, { "charNum": "46", "label": "사실형", "length": 60, "text": "중견 건설사 재무담당 임원 A씨, 건설업체 퇴출이 초읽기에 들어가면서 그는 요즘 속이 바짝바짝 타 들어간다.", "value": { "text_id": "2", "word_num": 15, "핵심동사": "타", "확실성": "확실", "극성": "긍정", "시제": "현재", "key_word": " " } }, { "charNum": "106", "label": "추론형", "length": 29, "text": "회사 생존이 걸려 있는 절체절명의 위기이기 때문이다.", "value": { "text_id": "3", "word_num": 7, "핵심동사": "때문이다", "확실성": "확실", "극성": "긍정", "시제": "현재", "key_word": "때문이다" } }, { "charNum": "135", "label": "사실형", "length": 54, "text": "외환위기(IMF) 때도 이 회사에서 근무했던 그는 그때보다 지금이 10배는 힘든 것 같다고 했다.", "value": { "text_id": "4", "word_num": 13, "핵심동사": "했다", "확실성": "확실", "극성": "긍정", "시제": "과거", "key_word": " " } }, { "charNum": "189", "label": "사실형", "length": 95, "text": "최근 은행연합회에서 내놓은 구조조정 평가 기준으로 회사 측이 시뮬레이션을 해본 결과 ＇안정권＇이라고 평가를 내렸지만 은행 평가는 다를 수 있기 때문에 조바심을 내고 있다.", "value": { "text_id": "5", "word_num": 23, "핵심동사": "내고", "확실성": "확실", "극성": "긍정", "시제": "현재", "key_word": " " } }, { "charNum": "284", "label": "사실형", "length": 83, "text": "등급을 매기는 데 비재무적 항목 비율이 60%를 차지하다 보니 매일 아침 주채권은행에 들러 분양률, 자구계획, 우발채무 변동상황 등을 설명하고 있다.", "value": { "text_id": "6", "word_num": 20, "핵심동사": "설명하고", "확실성": "확실", "극성": "긍정", "시제": "현재", "key_word": " " } }, { "charNum": "367", "label": "사실형", "length": 43, "text": "A씨는 오전 7시에 출근해 회사 자금상황을 파악한 후 10시쯤 외근을 나간다.", "value": { "text_id": "7", "word_num": 11, "핵심동사": "나간다", "확실성": "확실", "극성": "긍정", "시제": "현재", "key_word": " " } }, { "charNum": "410", "label": "사실형", "length": 42, "text": "은행, 증권사, 자산운용사 등 자금 조달이 가능한 곳이라면 어디든 방문한다.", "value": { "text_id": "8", "word_num": 10, "핵심동사": "방문한다", "확실성": "확실", "극성": "긍정", "시제": "현재", "key_word": " " } }, { "charNum": "452", "label": "사실형", "length": 49, "text": "하지만 시기가 모호하다 보니 발바닥이 닳도록 뛰어다녀도 별 신통한 성과를 얻기가 힘들다.", "value": { "text_id": "9", "word_num": 12, "핵심동사": "힘들다", "확실성": "확실", "극성": "부정", "시제": "현재", "key_word": " " } }, { "charNum": "501", "label": "사실형", "length": 47, "text": "신용평가사에도 들러 앞으로 자금조달 계획을 설명하며 신용등급 하향을 막아보려 애쓴다.", "value": { "text_id": "10", "word_num": 10, "핵심동사": "애쓴다", "확실성": "확실", "극성": "긍정", "시제": "현재", "key_word": " " } }, { "charNum": "548", "label": "사실형", "length": 61, "text": "신규 차입이나 자금 연장에 대해 읍소하면서 돌아다니다 회사에 돌아오면 밤 9~10시가 훌쩍 넘어버리기 일쑤다.", "value": { "text_id": "11", "word_num": 14, "핵심동사": "넘어버리기", "확실성": "확실", "극성": "긍정", "시제": "현재", "key_word": " " } }, { "charNum": "609", "label": "사실형", "length": 60, "text": "하지만 금융회사에 들러 신규 차입 의사를 타진하면 `대주단 평가가 끝나고 보자.`는 냉정한 답변이 돌아온다.", "value": { "text_id": "12", "word_num": 14, "핵심동사": "돌아온다", "확실성": "확실", "극성": "긍정", "시제": "미래", "key_word": " " } }, { "charNum": "669", "label": "사실형", "length": 55, "text": "심지어 아파트를 분양받은 사람들도 회사 등급 나오는 것을 보고 분양대금을 내겠다고 버티기까지 한다.", "value": { "text_id": "13", "word_num": 13, "핵심동사": "버티기까지", "확실성": "확실", "극성": "긍정", "시제": "현재", "key_word": " " } }, { "charNum": "724", "label": "사실형", "length": 49, "text": "분양대금 회수도 쉽지 않고 자금 조달도 안 되다 보니 회사 살림 꾸리기는 더 빡빡해졌다.", "value": { "text_id": "14", "word_num": 14, "핵심동사": "빡빡해졌다", "확실성": "확실", "극성": "부정", "시제": "과거", "key_word": " " } }, { "charNum": "773", "label": "사실형", "length": 34, "text": "신생 조선소인 A조선소 사장도 요즘 속이 까맣게 타 들어간다.", "value": { "text_id": "15", "word_num": 9, "핵심동사": "타", "확실성": "확실", "극성": "긍정", "시제": "현재", "key_word": " " } }, { "charNum": "807", "label": "사실형", "length": 38, "text": "꼼꼼히 구조조정 기준을 바탕으로 점검을 해보니 불안감은 더욱 커졌다.", "value": { "text_id": "16", "word_num": 9, "핵심동사": "커졌다", "확실성": "확실", "극성": "긍정", "시제": "과거", "key_word": " " } }, { "charNum": "845", "label": "사실형", "length": 24, "text": "구조조정 기준에 대부분이 해당하기 때문이다.", "value": { "text_id": "17", "word_num": 5, "핵심동사": "때문이다", "확실성": "확실", "극성": "긍정", "시제": "현재", "key_word": " " } }, { "charNum": "869", "label": "추론형", "length": 63, "text": "선박 인도 경험도 없고, 선박 건조 설비도 완료되지 못한 상태이기 때문에 ＇살생부＇에 오를 가능성이 높아 보인다.", "value": { "text_id": "18", "word_num": 16, "핵심동사": "보인다", "확실성": "불확실", "극성": "미정", "시제": "미래", "key_word": "보인다" } }, { "charNum": "932", "label": "추론형", "length": 30, "text": "기준대로라면 C등급을 받는 것만으로 다행스러운 처지다.", "value": { "text_id": "19", "word_num": 6, "핵심동사": "처지다", "확실성": "확실", "극성": "긍정", "시제": "현재", "key_word": "처지다" } }, { "charNum": "962", "label": "사실형", "length": 53, "text": "A조선소 사장은 주거래은행 등 채권단에 백방으로 문의를 해봤지만 시원스러운 답변을 얻지 못했다.", "value": { "text_id": "20", "word_num": 12, "핵심동사": "얻지", "확실성": "확실", "극성": "부정", "시제": "과거", "key_word": " " } }, { "charNum": "1015", "label": "사실형", "length": 48, "text": "`아직 아무것도 정해진 게 없으니 기다리라.`는 말 외에는 어떤 것도 들을 수가 없다.", "value": { "text_id": "21", "word_num": 13, "핵심동사": "들을", "확실성": "확실", "극성": "부정", "시제": "현재", "key_word": " " } }, { "charNum": "1063", "label": "사실형", "length": 44, "text": "심사 결과가 나올 때까지는 할 수 있는 게 아무것도 없다는 생각에 더욱 괴롭다.", "value": { "text_id": "22", "word_num": 13, "핵심동사": "괴롭다", "확실성": "확실", "극성": "긍정", "시제": "현재", "key_word": " " } }, { "charNum": "1107", "label": "사실형", "length": 77, "text": "A조선소 사장은 `중소 조선업체들은 대부분 비슷한 처지일 것`이라며 `가만히 앉아서 생사를 기다려야 하는 것이 안타까울 뿐`이라고 말했다.", "value": { "text_id": "23", "word_num": 17, "핵심동사": "말했다", "확실성": "확실", "극성": "긍정", "시제": "과거", "key_word": " " } }, { "charNum": "1184", "label": "사실형", "length": 27, "text": "이미 워크아웃에 들어간 C&중공업은 더 절박하다.", "value": { "text_id": "24", "word_num": 6, "핵심동사": "절박하다", "확실성": "확실", "극성": "긍정", "시제": "현재", "key_word": " " } }, { "charNum": "1211", "label": "사실형", "length": 50, "text": "임병석 회장 등 임원진은 채권단 관계자들을 만나기 위해 상가도 마다하지 않고 찾아 다닌다.", "value": { "text_id": "25", "word_num": 13, "핵심동사": "다닌다", "확실성": "확실", "극성": "긍정", "시제": "현재", "key_word": " " } }, { "charNum": "1261", "label": "사실형", "length": 64, "text": "임 회장을 비롯한 전 임원진이 주채권은행인 우리은행 등 채권단을 직접 찾아가 원활한 워크아웃 진행을 호소하고 있다.", "value": { "text_id": "26", "word_num": 16, "핵심동사": "호소하고", "확실성": "확실", "극성": "긍정", "시제": "현재", "key_word": " " } }, { "charNum": "1325", "label": "추론형", "length": 56, "text": "C&중공업은 이번 111개사 평가 대상에 포함돼 긍정적인 결과를 얻으면 극적인 자금 지원이 가능하다.", "value": { "text_id": "27", "word_num": 13, "핵심동사": "가능하다", "확실성": "불확실", "극성": "미정", "시제": "미래", "key_word": "가능하다" } }, { "charNum": "1381", "label": "사실형", "length": 17, "text": "하지만 상황은 그리 밝지 않다.", "value": { "text_id": "28", "word_num": 5, "핵심동사": "밝지", "확실성": "확실", "극성": "부정", "시제": "현재", "key_word": " " } }, { "charNum": "1398", "label": "사실형", "length": 39, "text": "한편 건설·조선업체 직원들 방문에 시중은행들도 어려움을 호소하고 있다.", "value": { "text_id": "29", "word_num": 8, "핵심동사": "호소하고", "확실성": "확실", "극성": "긍정", "시제": "현재", "key_word": " " } }, { "charNum": "1437", "label": "추론형", "length": 40, "text": "개별 사정을 들어보면 모두 도와주고 싶지만 사정이 여의치 않기 때문이다.", "value": { "text_id": "30", "word_num": 10, "핵심동사": "때문이다", "확실성": "확실", "극성": "부정", "시제": "현재", "key_word": "때문이다" } }, { "charNum": "1477", "label": "사실형", "length": 123, "text": "한 은행 관계자는 `얼마 전 한 모임에 나갔더니 어떻게 알고 왔는지 평가 대상 기업 직원들이 모두 찾아와 명함을 안기고 가더라`며 `그날 받은 명함만 수십 장인데 원하는 대로 지원하기 어려워 우리도 안타깝다.`고 말했다.", "value": { "text_id": "31", "word_num": 32, "핵심동사": "말했다", "확실성": "확실", "극성": "긍정", "시제": "과거", "key_word": " " } } ], "dupLabelYn": "Y", "metaData": { "ID": "130383", "FILENAME": "130383.json", "MEDIA_TYPE": "뉴스", "MEDIA_NAME": "매일경제", "CATEGORY": "금융", "PUBDATE": "20090108", "SENTENCE": "31" } } 