{ "annotation": [ { "charNum": "1", "label": "사실형", "length": 145, "text": "한국채택국제회계기준(기업회계기준서 제1016호)에 따르면 유형자산의 평가는 유형자산을 취득할 때에 취득원가로 인식한 후, 유형자산을 원가모형(cost model)이나 재평가모형(revaluation model) 중에서 어느 한 방법을 선택하여 평가할 수 있다.", "value": { "text_id": "1", "word_num": 24, "핵심동사": "평가할", "확실성": "확실", "극성": "긍정", "시제": "미래", "key_word": " " } }, { "charNum": "146", "label": "추론형", "length": 120, "text": "재평가모형은 원가모형과는 다르게 유형자산을 공정가치로 평가하는 방법으로, 기업이 재평가모형을 채택한 경우에는 개별 자산별로 재평가모형을 적용할 수 없고, 당해 자산이 포함되는 유형자산 분류 전체를 재평가하여야 한다.", "value": { "text_id": "2", "word_num": 25, "핵심동사": "재평가하여야", "확실성": "확실", "극성": "긍정", "시제": "미래", "key_word": "재평가하여야" } }, { "charNum": "266", "label": "사실형", "length": 139, "text": "기업의 투자 부문(investment center)별 단기 성과평가에 사용 가능한 지표는 투자수익률(return on investment), 잔여이익(residual income), 경제적 부가가치(economic value added) 등이 있다.", "value": { "text_id": "3", "word_num": 20, "핵심동사": "있다", "확실성": "확실", "극성": "긍정", "시제": "현재", "key_word": " " } }, { "charNum": "405", "label": "사실형", "length": 53, "text": "투자수익률은 ＇이익·투자자본＇으로 계산되며, 투자자본이 얼마나 효과적으로 운용되었는지 나타낸다.", "value": { "text_id": "4", "word_num": 8, "핵심동사": "나타낸다", "확실성": "확실", "극성": "긍정", "시제": "현재", "key_word": " " } }, { "charNum": "458", "label": "추론형", "length": 115, "text": "그러나 투자수익률은 계산식에서 투자자본의 자본비용을 직접적으로 고려하지 않음으로써 경영자가 의사결정 시 투자자본의 자본비용이 아닌 투자 부문의 현재투자수익률을 평가기준으로 사용하는 문제를 발생시킬 수 있다.", "value": { "text_id": "5", "word_num": 23, "핵심동사": "발생시킬", "확실성": "불확실", "극성": "미정", "시제": "미래", "key_word": "발생시킬" } }, { "charNum": "573", "label": "사실형", "length": 86, "text": "잔여이익은 ＇이익-(투자자본×최소필수자본비용)＇으로 계산되므로 최소필수자본비용이 계산에 포함돼 있어 위에 설명한 투자수익률과 같은 문제는 발생하지 않는다.", "value": { "text_id": "6", "word_num": 14, "핵심동사": "발생하지", "확실성": "확실", "극성": "부정", "시제": "현재", "key_word": " " } }, { "charNum": "659", "label": "사실형", "length": 101, "text": "경제적 부가가치는 ＇세후 이익-(투자자본×가중평균세후자본비용)＇으로 계산되며, 특히 다른 평가지표와는 달리 투자자본의 결정시 총자산에서 (이자 미발생) 단기부채를 차감하여 계산한다.", "value": { "text_id": "7", "word_num": 17, "핵심동사": "계산하다", "확실성": "확실", "극성": "긍정", "시제": "현재", "key_word": " " } } ], "dupLabelYn": "Y", "metaData": { "ID": "130812", "FILENAME": "130812.json", "MEDIA_TYPE": "뉴스", "MEDIA_NAME": "매일경제", "CATEGORY": "금융", "PUBDATE": "20100121", "SENTENCE": "7" } } 